pyspark_environment.py
databricks_environment-0.1.3.dist-info/LICENSE
databricks_environment-0.1.3.dist-info/METADATA
databricks_environment-0.1.3.dist-info/WHEEL
databricks_environment-0.1.3.dist-info/RECORD
