Metadata-Version: 2.1
Name: databricks-environment
Version: 0.1.3
Summary: Databricks Environment for pyspark apps
License: MIT
Author: DataSentics Team
Requires-Python: >=3.10,<4.0
Classifier: License :: OSI Approved :: MIT License
Classifier: Programming Language :: Python :: 3
Classifier: Programming Language :: Python :: 3.10
Classifier: Programming Language :: Python :: 3.11
Classifier: Programming Language :: Python :: 3.12
